discussion/__init__.py
discussion-0.0.1.dist-info/LICENSE
discussion-0.0.1.dist-info/METADATA
discussion-0.0.1.dist-info/WHEEL
discussion-0.0.1.dist-info/top_level.txt
discussion-0.0.1.dist-info/RECORD
